breakout_package/__init__.py
breakout_package/breakout.py
breakout_package-0.1.dist-info/METADATA
breakout_package-0.1.dist-info/WHEEL
breakout_package-0.1.dist-info/top_level.txt
breakout_package-0.1.dist-info/RECORD
